fruit_styles/__init__.py
fruit_styles/__pycache__/__init__.cpython-38.pyc
fruit_styles/avocado/avocado.css
fruit_styles/avocado/avocado.jpg
fruit_styles/avocado/conf.json
fruit_styles/avocado/index.html.j2
fruit_styles/nbconvert_example_template.egg-info/PKG-INFO
fruit_styles/nbconvert_example_template.egg-info/SOURCES.txt
fruit_styles/nbconvert_example_template.egg-info/dependency_links.txt
fruit_styles/nbconvert_example_template.egg-info/entry_points.txt
fruit_styles/nbconvert_example_template.egg-info/requires.txt
fruit_styles/nbconvert_example_template.egg-info/top_level.txt
nbconvert_example_template-0.1.dist-info/LICENSE
nbconvert_example_template-0.1.dist-info/METADATA
nbconvert_example_template-0.1.dist-info/WHEEL
nbconvert_example_template-0.1.dist-info/entry_points.txt
nbconvert_example_template-0.1.dist-info/top_level.txt
nbconvert_example_template-0.1.dist-info/RECORD
