Metadata-Version: 2.1
Name: nbconvert-example-template
Version: 0.1
Summary: A minimal and pip-installable nbconvert template example.
Home-page: https://github.com/sheeshee/nbconvert-template-example
Author: Samuel Sheehy
Author-email: samuelsheeh95@gmail.com
License: MIT
Platform: UNKNOWN
Classifier: Programming Language :: Python :: 3.7
Classifier: Programming Language :: Python :: 3.8
Classifier: Programming Language :: Python :: 3.9
Classifier: License :: OSI Approved :: MIT License
Classifier: Operating System :: OS Independent
Requires-Python: >=3.7
License-File: LICENSE
Requires-Dist: jupyter
Requires-Dist: nbconvert (>=6.0)
